Workbook

Sheet Read me
A1: MPX Global — Security Implementation Tracker
A3: Purpose | B3: Every security control committed to in the MPX Global Rev 02 quotations, in one place. These are contractual deliverables, not suggestions: the quotations list them as included in scope, so a control that is not built is a scope shortfall rather than a defect.
A5: How to use it | B5: Work through the Controls sheet as you build. Fill the three yellow columns — Status, Evidence and Verified on. Keep it updated as you go; reconstructing it at the end is far harder than maintaining it.
A7: Columns you edit | B7: Status · Evidence (commit, file path or test name) · Verified on (date) · Notes
A8: Columns to leave | B8: ID · Category · Control as promised · Promised in · Implementation approach · How to verify
A10: Status values | B10: Not started · In progress · Done · N/A
A12: Example row | B12: Status: Done | Evidence: src/middleware/rbac.js + tests/rbac.spec.js, commit a1b2c3d | Verified on: 12/08/2026 | Notes: default-deny applied at router level, 3 legacy routes migrated
A14: Why evidence matters | B14: If a security question is ever raised — by the Client, a payment aggregator, a penetration tester or an insurer — the question will be "show me", not "tell me". A commit reference or a passing test answers it in seconds. Memory does not.
A16: Before go-live | B16: The quotations recommend an independent penetration test engaged by the Client, plus a mobile application security assessment before store submission. Complete this tracker first, then hand it to the tester as the scope baseline.
A18: Note on cyber insurance | B18: Insurers now ask for demonstrated security controls and incident response documentation as a condition of cover, not as a recommendation. This sheet is most of that evidence.

Sheet Controls
A1: ID | B1: Category | C1: Control as promised | D1: Promised in | E1: Implementation approach | F1: How to verify | G1: Status | H1: Evidence (commit / file / test) | I1: Verified on | J1: Notes
A2: A1 | B2: A · Authentication & access | C2: Passwords stored using a modern one-way hashing algorithm — never in plain text or reversible form | D2: Web quotation, p10 | E2: argon2id (preferred) or bcrypt with cost factor 12+. Hash on the server only. No MD5/SHA-1/SHA-256, no encryption — hashing must be one-way and salted per user. | F2: Read a user record straight from MongoDB: the password field must be an argon2/bcrypt digest. Confirm no endpoint or log ever returns it. | G2: Done | H2: src/services/password.service.js (argon2id, server-side only); tests/m1-auth-session.test.js (change-password audit carries no password material), tests/security-adversarial.test.js | I2: 2026-09-25 | J2: Hash never returned: baseSchema toJSON strip guard (tests/security-controls.test.js).
A3: A2 | B3: A · Authentication & access | C3: JWT with short expiry and refresh-token rotation | D3: Web p10 · App p6 | E3: Access token 15 min, refresh token 7 days. Rotate the refresh token on every use and store only its hash server-side. On reuse of an already-rotated token, revoke the whole token family. | F3: Decode a token and check exp. Use a refresh token twice — the second attempt must fail and kill the session family. | G3: Done | H3: src/services/token.service.js (JWT_ACCESS_TTL 15m; rotateRefreshToken: rotate on every use, reuse revokes the whole family); tests/auth.test.js "refresh rotates; reusing the old token revokes the whole family", tests/a2-refresh-cookie.test.js | I3: 2026-09-25 | J3: Web keeps the refresh token in an httpOnly cookie; the app keeps it in the secure keystore (G1).
A4: A3 | B4: A · Authentication & access | C4: OTP with expiry, attempt limits and rate limiting | D4: Web p10 · App p6 | E4: 6 digits, 5-minute expiry, maximum 5 attempts then a 15-minute lock. Store the OTP hashed, never in plain text. Rate limit per mobile, per email and per IP. | F4: Request 6 OTPs in a row — later requests must be throttled. Enter a wrong OTP 5 times and confirm the lock. | G4: Done | H4: src/services/otp.service.js + src/config/env.js (OTP_TTL_SECONDS 300, OTP_MAX_ATTEMPTS 5, OTP_LOCK_SECONDS 900), otpLimiter in src/middleware/rateLimit.js; tests/otp-lock.test.js (lock, durable lock, concurrent guesses, single use, expiry, purpose/user scope) | I4: 2026-09-25 | J4: Codes can also go to the account's own email ("Don't have your phone?"), and the lock survives the switch (tests/otp-email-channel.test.js).
A5: A4 | B5: A · Authentication & access | C5: Two-factor authentication available on Admin and Super Admin accounts | D5: Web quotation, p10 | E5: TOTP via otplib/speakeasy, enrolled with a QR code. Enforce at login for Admin and Super Admin roles. Issue single-use backup codes stored hashed. | F5: Log in as Super Admin without a TOTP code — must be refused. Confirm a backup code works once and then fails. | G5: N/A | H5: — | I5: 2026-09-25 | J5: WAIVED BY THE OWNER, 2026-09-25 ("no need of 2fa"). The Super Admin signs in with password + one-time code (two factors), like all staff. TOTP groundwork exists (tests/d4-twofactor-backup-codes.test.js) but is not enforced. Client sign-off on this waiver recommended.
A6: A5 | B6: A · Authentication & access | C6: Server-side RBAC enforced on every endpoint — permissions are not merely hidden in the interface | D6: Web p10 · App p6 | E6: A single permission middleware applied at the router level with default-deny. Every route declares its required permission; a route with no declaration must fail to start the server. | F6: Call an Admin-only endpoint with a Buyer's valid token — must return 403. Grep the codebase for routes without a permission declaration. | G6: Done | H6: src/config/routeGuard.js (assertRoutesGuarded at boot: a route with no public/auth/permission declaration stops the server), src/middleware/authorize.js; tests/routeGuard.test.js, tests/security-adversarial.test.js "privilege escalation", tests/m5-adversarial.test.js | I6: 2026-09-25 | J6: Staff permissions are per employee (24 permissions); "Admin" is not a role.
A7: A6 | B7: A · Authentication & access | C7: Ownership checks on every resource to prevent access to another user's records by ID manipulation | D7: Web p10 · App p6 | E7: Never query by _id alone. Every read/write scopes by owner: findOne({_id, ownerId: req.user.orgId}). Applies to deals, quotes, contracts, orders, shipments, documents and payouts. | F7: Take a valid deal ID belonging to Exporter A and request it as Exporter B — must return 404, not 403 (do not confirm the record exists). | G7: Done | H7: src/models/scoping.js (declareScope / scopedFilter; an undeclared model is refused); tests/security-controls.test.js "ownership scoping is DECLARED on every model", tests/security-adversarial.test.js "cross-tenant ownership (IDOR)", tests/bank-accounts.test.js, tests/support-tickets.test.js | I7: 2026-09-25 | J7: Another owner's record returns 404, never 403.
A8: A7 | B8: A · Authentication & access | C8: Sessions invalidated on password change, role change or deactivation | D8: Web p10 · App p6 | E8: Keep a tokenVersion integer on the user document; include it in the JWT and compare on every request. Increment it on password change, role change, deactivation and logout. | F8: Log in on two devices, change the password on one — the other device's next request must fail. | G8: Done | H8: src/middleware/authenticate.js (tokenVersion checked on every request), src/services/auth.service.js (password change/reset bump tokenVersion + revoke refresh tokens), src/services/userManagement.service.js:152 (deactivation bumps tokenVersion); tests/security-adversarial.test.js "stale tokenVersion", tests/m1-auth-session.test.js "kills every existing session" | I8: 2026-09-25 | J8: Known, recorded gap: plain LOGOUT revokes the refresh token but the current access token lives until it expires (max 15 min) — tests/m1-auth-session.test.js "KNOWN GAP".
A9: A8 | B9: A · Authentication & access | C9: Named user accounts throughout — no shared logins | D9: Web quotation, p10 | E9: Unique email per employee account. No generic shared accounts. Every audit entry records a named user id, never a role. | F9: Check the employee collection for shared or generic addresses. Confirm each audit row carries a user id. | G9: Done | H9: src/models/User.js (unique email per role; employees are individual accounts created by the Super Admin), src/services/audit.service.js (every entry carries actorId + actorRole); tests/userManagement.test.js, tests/m5-audit-viewer.test.js "resolves a real actor to a name and role" | I9: 2026-09-25 | J9: No generic shared staff accounts exist in the code; keep it that way operationally.
A10: B1 | B10: B · Application security | C10: Schema validation and sanitisation on all incoming data | D10: Web p10 · App p6 | E10: Validate every request body, query and param with zod or joi at the route boundary. Strip unknown keys rather than passing them through. Reject on failure before any business logic runs. | F10: Post an extra unexpected field to a write endpoint — it must not reach the database. | G10: Done | H10: src/middleware/validate.js (zod on body, params and query at the route boundary; unknown keys stripped, .strict() on sensitive bodies); tests/validate.test.js "strips unknown keys", tests/security-adversarial.test.js "mass assignment" | I10: 2026-09-25
A11: B2 | B11: B · Application security | C11: Database query sanitisation to prevent injection through user input | D11: Web quotation, p10 | E11: MongoDB operator injection is the real risk here: reject objects where a string is expected, so {"$gt":""} cannot be sent as a password. Use express-mongo-sanitize and never pass req.body straight into a query. | F11: Attempt a login with the password field set to {"$gt":""} — must be rejected as invalid input. | G11: Done | H11: src/middleware/rejectMongoOperators.js ($-keys and dotted keys refused before any handler), zString helper in src/validators/helpers.js; tests/validate.test.js, tests/security-adversarial.test.js "an operator object as a password does not authenticate anyone", "prototype-pollution keys" | I11: 2026-09-25
A12: B3 | B12: B · Application security | C12: Output encoding and content-security headers to prevent script injection | D12: Web quotation, p10 | E12: helmet with a Content-Security-Policy. React escapes by default — avoid dangerouslySetInnerHTML entirely, and sanitise any rich text with DOMPurify before rendering. | F12: Save a product name containing a script tag and open the product page — it must render as text. | G12: Done | H12: src/app.js (helmet with a Content-Security-Policy), web/vercel.json (CSP + security headers on the web); no dangerouslySetInnerHTML anywhere in web/src or app/src; tests/security-controls.test.js "helmet headers are present" | I12: 2026-09-25 | J12: React escapes user content by default.
A13: B4 | B13: B · Application security | C13: Cross-site request forgery protection | D13: Web quotation, p10 | E13: SameSite=Strict, HttpOnly, Secure cookies. If any state-changing route uses cookie auth, add a CSRF token (csurf or double-submit). Bearer-token-only routes are not exposed to CSRF. | F13: Submit a state-changing request from a different origin — must be rejected. | G13: Done | H13: Access tokens travel in the Authorization header, not a cookie. The only cookie-authenticated routes (refresh, logout) require a web-client header; tests/a2-refresh-cookie.test.js "SameSite=None CSRF guard" (cookie-borne refresh/logout without the header is refused) | I13: 2026-09-25 | J13: Refresh cookie (src/utils/refreshCookie.js): httpOnly, SameSite=Lax, Secure in production, scoped to /auth.
A14: B5 | B14: B · Application security | C14: Secure transport enforced end to end (HTTPS / HSTS) with hardened response headers | D14: Web p10 · App p6 | E14: TLS terminated at nginx with a redirect from HTTP. helmet for HSTS (with preload), X-Content-Type-Options, frame-ancestors, Referrer-Policy and Permissions-Policy. | F14: Run the domain through SSL Labs and securityheaders.com — target A or better on both. | G14: In progress | H14: src/app.js helmet hsts {maxAge 15552000, includeSubDomains, preload}; web/vercel.json Strict-Transport-Security | J14: Code side done. TLS termination + HTTP→HTTPS redirect on the VPS nginx is a deploy step (docs/Deployment.md); then run SSL Labs + securityheaders.com and record the grades here.
A15: B6 | B15: B · Application security | C15: File upload validation — type, size and content checks; uploads stored without execution rights | D15: Web p10 · App p6 | E15: Allowlist extensions, verify the MIME type against magic bytes (file-type package), cap size. Upload to Cloudinary rather than the app server. Never serve uploads from a directory that can execute. | F15: Rename a .js file to .jpg and upload it — must be rejected on content inspection, not just extension. | G15: Done | H15: src/services/kyc.storage.service.js (verifyKycFile), src/services/image.storage.service.js, src/services/chatAttachment.storage.service.js (file-type magic-byte allowlist, size caps, empty-file refusal, PDF script / Office macro screen); tests/kycStorage.test.js "rejects a spoofed file", tests/chat-documents.test.js, tests/m2-image-refs.test.js | I15: 2026-09-25 | J15: Files are stored on Cloudinary, never on the app server; KYC and chat files are PRIVATE assets.
A16: B7 | B16: B · Application security | C16: Rate limiting on authentication, OTP, search and AI endpoints | D16: Web p10 · App p6 | E16: express-rate-limit backed by Redis so limits hold across restarts and multiple processes. Tighter per-account limits on auth and OTP; per-org quota on the AI endpoints to cap GPT spend. | F16: Script 100 rapid requests at /login and at the AI endpoint — both must start returning 429. | G16: Done | H16: src/middleware/rateLimit.js (express-rate-limit + Redis store, REQUIRED in production): auth, OTP, refresh, search, AI, upload, enquiry, message, ticket, unblock limiters; tests/a2-refresh-cookie.test.js "refresh has its OWN budget", tests/m3-ai-quota.test.js | I16: 2026-09-25 | J16: Per-user keys on signed-in routes, per-IP on public ones.
A17: B8 | B17: B · Application security | C17: Generic error responses — no stack traces or internal detail exposed to users | D17: Web p10 · App p6 | E17: One central error handler. Return a generic message plus a request id; log the full detail server-side against that id. Never return a Mongo error verbatim. | F17: Force a database error in staging — the API response must contain no stack trace, collection name or driver text. | G17: Done | H17: src/middleware/errorHandler.js (one central handler: generic message + requestId, full detail only in the server log / errorLogs); tests/security-controls.test.js "central error handler never leaks internals" | I17: 2026-09-25
A18: B9 | B18: B · Application security | C18: Dependency vulnerability scanning during development | D18: Web quotation, p10 | E18: npm audit in CI plus Dependabot or Snyk on the repository. Fail the build on high and critical findings. Re-run before every milestone demo. | F18: Attach the latest scan output showing zero unresolved high or critical issues. | G18: In progress | H18: npm audit run 2026-09-25. Backend: 3 HIGH fixed the same day (multer 2.4.0, nodemailer 9.1.1, ip-address 10.7.2 — patch/minor, within existing ranges; full suite 1391/1391 green after). Now 0 high, 0 critical, 9 moderate. Web: 0 high, 2 moderate. | J18: Still to do: add npm audit to CI + Dependabot (no CI pipeline exists in the repo yet). 8 of the 9 backend moderates come through firebase-admin and need a MAJOR upgrade (v14) — owner decision.
A19: C1 | B19: C · Payment & escrow | C19: Payout beneficiaries registered with the provider and referenced by token, so bank details in the platform database are display-only and cannot redirect a payment | D19: Web quotation, p10 | E19: Register the beneficiary with the gateway and store only the provider's token plus the masked last four digits. Every payout call sends the token, never an account number held by us. | F19: Change a bank account number directly in MongoDB and trigger a payout — the money must still go to the provider-registered account. | G19: N/A | H19: — | I19: 2026-09-25 | J19: Phase 2 (escrow, payouts, contracts) is not built in Phase 1 (docs/scope-of-work.md, month1-not-doing.md Bucket B). Nothing in Phase 1 moves money. NOTE: the quotation module stores exporter bank details for quotations (models/ExporterBankAccount.js: accountNumber select:false, only last4 ever returned, every change audited — tests/bank-accounts.test.js). No payout is ever sent from them. When Phase 2 builds payouts, this control must be implemented as written (provider token, not our stored number).
A20: C2 | B20: C · Payment & escrow | C20: Release requires authorisation outside the platform — provider-side payout approval under the Client's control, protected by their own two-factor authentication | D20: Web quotation, p10 | E20: The platform records intent and approval; the actual release is confirmed in the gateway dashboard by the Client's authorised user. No credential we hold can release funds on its own. | F20: Confirm with the Client that provider-side payout approval and 2FA are switched on, and record the confirmation in writing. | G20: N/A | H20: — | I20: 2026-09-25 | J20: Phase 2 (escrow, payouts, contracts) is not built in Phase 1 (docs/scope-of-work.md, month1-not-doing.md Bucket B). Nothing in Phase 1 moves money.
A21: C3 | B21: C · Payment & escrow | C21: Idempotency keys on every payout and release call, preventing duplicate disbursement under repeated or concurrent requests | D21: Web quotation, p10 | E21: Deterministic key per (dealId, milestoneId, attempt). Unique index in MongoDB so a duplicate insert fails, and send the same key as the provider's idempotency header. | F21: Fire the same release request 10 times concurrently — exactly one payout must be created. | G21: N/A | H21: — | I21: 2026-09-25 | J21: Phase 2 (escrow, payouts, contracts) is not built in Phase 1 (docs/scope-of-work.md, month1-not-doing.md Bucket B). Nothing in Phase 1 moves money.
A22: C4 | B22: C · Payment & escrow | C22: Cryptographic signature verification on all payment provider webhooks — forged callbacks are rejected | D22: Web quotation, p10 | E22: Verify the HMAC against the raw body before parsing JSON. Reject unknown event ids and anything outside a 5-minute timestamp window to stop replay. | F22: Post a webhook with a tampered body and a valid-looking signature — must be rejected and logged. | G22: N/A | H22: — | I22: 2026-09-25 | J22: Phase 2 (escrow, payouts, contracts) is not built in Phase 1 (docs/scope-of-work.md, month1-not-doing.md Bucket B). Nothing in Phase 1 moves money. No payment webhook exists.
A23: C5 | B23: C · Payment & escrow | C23: Cooling-off period enforced after any change to a payout account before a release can proceed | D23: Web p10 · App p6 | E23: Stamp the account record on change and block any release to it for a fixed window (48 hours suggested). Enforce server-side, not in the UI. | F23: Change a payout account and immediately attempt a release — must be blocked with the reason shown. | G23: N/A | H23: — | I23: 2026-09-25 | J23: Phase 2 (escrow, payouts, contracts) is not built in Phase 1 (docs/scope-of-work.md, month1-not-doing.md Bucket B). Nothing in Phase 1 moves money.
A24: C6 | B24: C · Payment & escrow | C24: Out-of-band alerts on bank account change and on every payout, sent to previously registered contacts | D24: Web quotation, p10 | E24: On change, notify the OLD email and mobile, not the new one. On every payout, notify the exporter and the Client's admin over email, SMS and WhatsApp. | F24: Change an account and confirm the alert lands on the previous contact details. | G24: N/A | H24: — | I24: 2026-09-25 | J24: Phase 2 (escrow, payouts, contracts) is not built in Phase 1 (docs/scope-of-work.md, month1-not-doing.md Bucket B). Nothing in Phase 1 moves money.
A25: C7 | B25: C · Payment & escrow | C25: Beneficiary name verification against registered company records before an account is usable | D25: Web quotation, p10 | E25: Penny-drop through the gateway, then fuzzy-match the returned account holder name against the registered company name. Block the account until it matches or an admin overrides with a logged reason. | F25: Add an account whose holder name differs from the company name — it must not become usable silently. | G25: N/A | H25: — | I25: 2026-09-25 | J25: Phase 2 (escrow, payouts, contracts) is not built in Phase 1 (docs/scope-of-work.md, month1-not-doing.md Bucket B). Nothing in Phase 1 moves money.
A26: C8 | B26: C · Payment & escrow | C26: Maker–checker separation and a distinct approval permission for escrow release | D26: Web quotation, p7 & p10 | E26: escrow.approve as its own permission, assignable separately from every other employee permission. Code check: raisedBy must not equal approvedBy. | F26: Raise a release request and try to approve it with the same account — must be refused. | G26: N/A | H26: — | I26: 2026-09-25 | J26: Phase 2 (escrow, payouts, contracts) is not built in Phase 1 (docs/scope-of-work.md, month1-not-doing.md Bucket B). Nothing in Phase 1 moves money.
A27: C9 | B27: C · Payment & escrow | C27: Per-transaction and daily release caps | D27: Web quotation, p10 | E27: Configurable caps per exporter and platform-wide, checked server-side before the release call. Anything above the threshold requires mandatory approval regardless of other rules. | F27: Attempt a release above the cap — must be blocked or forced into the approval queue. | G27: N/A | H27: — | I27: 2026-09-25 | J27: Phase 2 (escrow, payouts, contracts) is not built in Phase 1 (docs/scope-of-work.md, month1-not-doing.md Bucket B). Nothing in Phase 1 moves money.
A28: C10 | B28: C · Payment & escrow | C28: Append-only approval and transaction audit trail, written with insert-only database privileges | D28: Web quotation, p10 | E28: Separate audit collection. The application's database user has insert and find only on it — no update, no delete. No API route exists that can modify an audit record. | F28: Try to update an audit document through the app's own database connection — must be denied by the database, not just the code. | G28: In progress | H28: App side: no endpoint, script or service updates or deletes an AuditLog row (src/services/audit.service.js is insert-only); tests/m5-audit-viewer.test.js "there is NO write, update or delete route" | J28: Phase 1 already audits approvals, verifications, takedowns, permission changes. Remaining: the database-level insert+find-only grant for the app's MongoDB user on the audit collection — a deploy step on the self-hosted MongoDB (docs/Deployment.md). Same step closes E4.
A29: C11 | B29: C · Payment & escrow | C29: Critical audit events mirrored to storage outside the application server | D29: Web quotation, p10 | E29: Stream approvals, payouts and account changes to external storage (S3 or an equivalent) as they happen, so a compromised server cannot erase the record. | F29: Confirm today's approval events exist in the external store as well as the database. | G29: N/A | H29: — | I29: 2026-09-25 | J29: Phase 2 (escrow, payouts, contracts) is not built in Phase 1 (docs/scope-of-work.md, month1-not-doing.md Bucket B). Nothing in Phase 1 moves money. (Revisit with Phase 2: mirror approval/payout events off-server.)
A30: C12 | B30: C · Payment & escrow | C30: Daily automated reconciliation against the provider ledger with mismatch alerting | D30: Web quotation, p7 & p10 | E30: Scheduled job comparing the platform escrow ledger with the provider's settlement report. Any mismatch raises an alert to the Client's admin and is recorded. | F30: Introduce a deliberate mismatch in staging — the job must flag it the next run. | G30: N/A | H30: — | I30: 2026-09-25 | J30: Phase 2 (escrow, payouts, contracts) is not built in Phase 1 (docs/scope-of-work.md, month1-not-doing.md Bucket B). Nothing in Phase 1 moves money.
A31: D1 | B31: D · Contract & eSign integrity | C31: Document generated once, then version-locked and hash-sealed — both parties sign the identical artifact | D31: Web quotation, p8 | E31: Store a SHA-256 of the generated PDF at creation. Verify the hash before presenting for signature and again after signing. Any mismatch blocks the flow. | F31: Alter a stored contract file byte-for-byte and open it — the system must detect the hash mismatch. | G31: N/A | H31: — | I31: 2026-09-25 | J31: Contracts / eSign are Phase 2 (Bucket B). The quotation PDF built in Phase 1 is not a contract and carries no signature.
A32: D2 | B32: D · Contract & eSign integrity | C32: Any amendment creates a new version and invalidates prior signatures; all versions retained | D32: Web quotation, p8 | E32: Versioned contract documents. Amending creates v2 and marks v1 superseded; signatures never carry across versions. Nothing is deleted. | F32: Amend a signed contract — the earlier signatures must show as invalidated and v1 must still be retrievable. | G32: N/A | H32: — | I32: 2026-09-25 | J32: Contracts / eSign are Phase 2 (Bucket B).
A33: D3 | B33: D · Contract & eSign integrity | C33: Values snapshotted at generation, so later catalogue or price edits cannot alter a signed contract | D33: Web quotation, p8 | E33: The contract stores its own copy of parties, goods, quantity, unit price, currency and total — never a live reference to the catalogue. | F33: Change the product price after a contract is generated and reopen the contract — the figures must not move. | G33: N/A | H33: — | I33: 2026-09-25 | J33: Contracts / eSign are Phase 2 (Bucket B). Note: quotations already snapshot their figures (tests/quotations.test.js, tests/quotation-totals.test.js).
A34: D4 | B34: D · Contract & eSign integrity | C34: Expired quotations cannot generate a contract | D34: Web quotation, p8 | E34: Server-side validity check at generation time, not a UI-only guard. | F34: Call the generate endpoint directly with an expired quotation id — must be refused. | G34: N/A | H34: — | I34: 2026-09-25 | J34: Contracts are Phase 2 — no contract generation exists.
A35: D5 | B35: D · Contract & eSign integrity | C35: Signing OTP with expiry and attempt limits; signing links expire and can be re-issued | D35: Web quotation, p8 | E35: Single-use signed token in the link with a short TTL. OTP sent to the registered signatory email only — never to an address supplied in the request. | F35: Reuse a signing link after signing, and after expiry — both must fail. | G35: N/A | H35: — | I35: 2026-09-25 | J35: Contracts / eSign are Phase 2 (Bucket B).
A36: D6 | B36: D · Contract & eSign integrity | C36: Audit certificate appended to every executed contract — signatory email, timestamps, IP, verification method and document hash | D36: Web quotation, p8 | E36: Generate the certificate page at completion and merge it into the executed PDF, then re-hash and store the final artifact. | F36: Open an executed contract and confirm the certificate page carries all five fields. | G36: N/A | H36: — | I36: 2026-09-25 | J36: Contracts / eSign are Phase 2 (Bucket B).
A37: D7 | B37: D · Contract & eSign integrity | C37: Escrow funding unlocks only after both signatures are captured | D37: Web quotation, p8 | E37: Server-side state check on the funding endpoint. The UI hiding the button is not sufficient. | F37: Call the funding endpoint directly on a half-signed deal — must be refused. | G37: N/A | H37: — | I37: 2026-09-25 | J37: Escrow funding is Phase 2 (Bucket B).
A38: E1 | B38: E · Data protection | C38: Encryption in transit throughout; encryption at rest for sensitive fields including payout details and KYC documents | D38: Web quotation, p11 | E38: TLS everywhere. Field-level encryption for payout details and KYC identifiers, with the key held outside the database. Cloudinary storage for KYC documents, private mode. | F38: Read the raw collection — payout and KYC fields must be unreadable without the key. | G38: In progress | H38: In transit: HTTPS enforced by HSTS (B5) and the app blocks cleartext (G5). KYC files: Cloudinary PRIVATE assets. Bank account number: select:false, never returned (models/ExporterBankAccount.js). | J38: OWNER DECISION 2026-09-25: field-level encryption of the bank account number is NOT being done (plan offered: AES-256-GCM, key in env; declined). The number stays plain text in MongoDB, protected by select:false, last4-only responses/audit and log redaction. Options still open: MongoDB encryption at rest on the VPS disk. TLS in transit is a deploy step (B5). Client sign-off recommended, as this is a quoted control.
A39: E2 | B39: E · Data protection | C39: Bank account numbers displayed masked; full reveal is a logged, permissioned action | D39: Web p11 · App p6 | E39: Masked by default everywhere including the approval screen. Reveal is a separate permissioned endpoint that writes an audit entry naming the user, record and time. | F39: Reveal an account number and confirm the audit entry appears. | G39: Done | H39: models/ExporterBankAccount.js (only last4 in every list/response); tests/bank-accounts.test.js "never returns the account number", "audits every change with last4 and NEVER the account number"; mobile numbers masked (tests/mask.test.js) | I39: 2026-09-25 | J39: There is no full-reveal action at all in Phase 1 — stricter than the control. Payout-account masking returns with Phase 2.
A40: E3 | B40: E · Data protection | C40: Documents stored with signed, expiring access links rather than public URLs | D40: Web quotation, p11 | E40: Cloudinary signed delivery URLs with a short TTL, generated per request after an authorisation check. No document reachable by guessing a URL. | F40: Copy a document URL, wait past its TTL, and open it in a private window — must fail. | G40: Done | H40: src/services/kyc.storage.service.js (Cloudinary type:private, randomised public_id, 120 s signed URLs minted only after an authorisation check); chat attachments use the same private pattern (src/services/chatAttachment.storage.service.js); tests/kycStorage.test.js "mints a SHORT-LIVED signed url", tests/chat-documents.test.js | I40: 2026-09-25
A41: E4 | B41: E · Data protection | C41: Least-privilege database roles — the application cannot modify or delete audit and approval history | D41: Web quotation, p11 | E41: Two database users: the application user without update/delete on audit collections, and a separate maintenance user used only by an administrator. | F41: Attempt a delete on the audit collection with the application's credentials — must be denied. | G41: Not started | H41: Documented in docs/Deployment.md (app DB user: insert + find only on audit collections). | J41: Deploy step on the self-hosted production MongoDB: create the least-privilege app user, then try a delete on auditlogs with its credentials and record the refusal here.
A42: E5 | B42: E · Data protection | C42: No production data used in development or testing environments | D42: Web quotation, p11 | E42: Seeded or anonymised fixtures only. No production dump ever restored to staging or a local machine. | F42: Confirm the staging database contains no real buyer, exporter or KYC records. | G42: In progress | H42: Production starts on a fresh, empty database (owner, 2026-09-25); dev/test use test fixtures and throwaway accounts only. | J42: Confirm at deploy that staging holds no real buyer/exporter/KYC data, then mark Done.
A43: E6 | B43: E · Data protection | C43: Credentials and API keys held outside the codebase and never committed to version control | D43: Web quotation, p11 | E43: .env excluded by .gitignore from the first commit. Secrets in the VPS environment or a secret manager. Scan the full git history for anything already leaked, and rotate whatever is found. | F43: Run gitleaks or trufflehog over the entire history — zero findings, or rotated and documented. | G43: In progress | H43: .gitignore excludes every .env (root, backend, web, app); no secrets in source. .env is not tracked today. | J43: A backend .env with DEV-ONLY values was committed on 2026-07-31 (a486611) and removed later (77f7208). OWNER 2026-09-25: that .env is the developer's own dev file; production uses a separate, never-committed .env, so no production credential was exposed and no rotation is required for launch. History rewrite prepared (file purged from every commit, code identical); the owner runs the force-push. Remaining: run gitleaks/trufflehog over the full history before handover and record the result here.
A44: F1 | B44: F · Infrastructure & operations | C44: Separate staging and production environments | D44: Web quotation, p11 | E44: Distinct database, distinct API keys, distinct subdomain. Staging is never pointed at live payment credentials. | F44: Confirm the two environments share no credential and no database. | G44: Not started | H44: — | J44: Deploy step: separate staging and production (own database, own keys, own subdomain).
A45: F2 | B45: F · Infrastructure & operations | C45: Managed database with network-level access restriction, recommended and configured | D45: Web quotation, p11 | E45: MongoDB Atlas with an IP allowlist limited to the application server, or VPC peering. Never 0.0.0.0/0. Database not reachable from the public internet. | F45: Attempt a connection from an unlisted IP — must be refused. | G45: Not started | H45: docs/Deployment.md (net.bindIp 127.0.0.1, firewall blocks 27017) | J45: Production MongoDB is SELF-HOSTED on the VPS, not Atlas (§A26), so the control is met by bindIp + firewall rather than an Atlas IP allowlist. Verify at deploy with a connection attempt from outside.
A46: F3 | B46: F · Infrastructure & operations | C46: Database and payment credentials scoped to the application server only | D46: Web quotation, p11 | E46: No developer laptop and no other host holds production credentials. Local development uses its own database. | F46: Confirm no production secret exists in any local .env or shared document. | G46: Not started | H46: — | J46: Deploy/handover: production credentials live only on the VPS; local development uses the dev database.
A47: F4 | B47: F · Infrastructure & operations | C47: Automated backup schedule configured, with a documented restore procedure | D47: Web quotation, p11 | E47: Daily automated backups with a defined retention period, stored off the application server. Write the restore runbook and test it once before go-live. | F47: Perform a real restore into staging from a backup and record the date it was done. | G47: Not started | H47: — | J47: Deploy step: daily automated MongoDB backups off the server + a real restore into staging, dated here.
A48: F5 | B48: F · Infrastructure & operations | C48: Application and access logging with retention and time synchronisation aligned to CERT-In directions | D48: Web quotation, p11 | E48: NTP-synchronised clocks, ISO-8601 timestamps with timezone, and 180-day log retention held within India. Log authentication, authorisation failures, payouts and admin actions. | F48: Confirm NTP is active, retention is configured, and sample logs carry consistent timestamps. | G48: In progress | H48: src/utils/logger.js (pino, ISO timestamps, sensitive paths redacted); errorLogs kept 90 days (models/ErrorLog.js TTL); append-only AuditLog kept indefinitely | J48: Remaining for CERT-In: 180-day retention for application/access logs on the VPS (log rotation config) and NTP enabled. The 90-day error-log TTL is an internal diagnostics table, not the access log.
A49: F6 | B49: F · Infrastructure & operations | C49: Live payment credentials entered by the Client, not held by NxtGen Digitals | D49: Web quotation, p11 | E49: The Client enters production gateway keys themselves. We work against sandbox keys throughout. Record in writing that live keys were never shared with us. | F49: Written confirmation from the Client, kept on file. | G49: N/A | H49: — | I49: 2026-09-25 | J49: No payment gateway in Phase 1 (Phase 2).
A50: F7 | B50: F · Infrastructure & operations | C50: All production credentials transferred and rotated by the Client at handover | D50: Web quotation, p11 · Annexure A | E50: Handover checklist covering database, gateway, Cloudinary, WhatsApp BSP, OpenAI, VPS, domain, store accounts and signing keys. Client rotates each one and signs the checklist. | F50: Signed handover checklist with the rotation date against every item. | G50: Not started | H50: — | J50: At handover: signed checklist — database, Cloudinary, OpenAI, SMS/email provider, Firebase, VPS, domain — each rotated by the Client, with dates. (No payment gateway or WhatsApp BSP in Phase 1.)
A51: F8 | B51: F · Infrastructure & operations | C51: Post-handover maintenance performed under scoped, least-privilege access, granted for a defined window and rotated afterwards | D51: Web quotation, p11 | E51: No standing production access after handover. Access requested per task, time-boxed, and rotated by the Client when the window closes. | F51: Access request and revocation recorded for each maintenance visit. | G51: Not started | H51: — | J51: Post-handover process: access requested per task, time-boxed, revoked, logged.
A52: G1 | B52: G · Mobile app security | C52: Tokens and credentials stored in the platform secure keystore (Android Keystore / iOS Keychain), never in plain storage | D52: App quotation, p6 | E52: expo-secure-store for tokens and any credential. Never AsyncStorage, never Redux persisted to disk, never a plain file. | F52: Inspect app storage on a rooted or jailbroken test device — no token in readable form. | G52: Done | H52: app/src/api/tokenStore.js + app/src/utils/secureStorage.js (expo-secure-store); no token in AsyncStorage | I52: 2026-09-25 | J52: Needs a device check (rooted/jailbroken inspection) before store release.
A53: G2 | B53: G · Mobile app security | C53: Optional biometric / device unlock for app re-entry | D53: App quotation, p6 | E53: expo-local-authentication, user-toggleable in settings. Biometrics gate re-entry only — never replace server-side authentication. | F53: Enable it, background the app, reopen — the prompt must appear. | G53: Not started | H53: expo-local-authentication is installed (app/package.json); the re-entry gate (design screen 17) is not built | J53: Deliberately no toggle until the gate exists (app/src/screens/ProfileScreen.jsx note, owner 2026-08-05). This is a quoted, optional feature still to build.
A54: G3 | B54: G · Mobile app security | C54: No sensitive data written to device logs or crash reports | D54: App quotation, p6 | E54: Strip tokens, OTPs, bank details and PII before any Sentry or console output. Disable verbose logging in release builds. | F54: Trigger a crash in a release build and inspect the report for leaked values. | G54: Done | H54: app/src/utils/logger.js (debug/info compile out of release builds via __DEV__; no token/OTP/password logged); backend logger redacts sensitive paths (src/utils/logger.js) | I54: 2026-09-25 | J54: No crash-reporting SDK (e.g. Sentry) is installed, so there is no third-party crash report to leak into.
A55: G4 | B55: G · Mobile app security | C55: Screenshot restriction on contract and payout screens | D55: App quotation, p6 | E55: FLAG_SECURE on Android for those screens; an overlay or blur on iOS when the app enters the background. | F55: Attempt a screenshot on the contract screen on both platforms. | G55: N/A | H55: — | I55: 2026-09-25 | J55: Contract and payout screens do not exist in Phase 1 (Phase 2).
A56: G5 | B56: G · Mobile app security | C56: Secure transport enforced end to end (HTTPS) | D56: App quotation, p6 | E56: No cleartext traffic: App Transport Security on iOS, network security config on Android. Consider certificate pinning for payment-related calls. | F56: Run the app through an intercepting proxy — traffic must fail rather than fall back to plain HTTP. | G56: Done | H56: app/app.config.js: iOS NSAllowsArbitraryLoads false, Android usesCleartextTraffic false; app/src/config/env.js refuses a non-https API URL in any release build (http only for a local dev build) | I56: 2026-09-25 | J56: Confirm with an intercepting proxy on a release build before store upload.
A57: G6 | B57: G · Mobile app security | C57: Role-based access enforced on the server for every request — the app never decides its own permissions | D57: App quotation, p6 | E57: The app renders from server-supplied permissions but every endpoint re-checks. Never trust a role claim held in app state. | F57: Patch the app build to claim the exporter role as a buyer account — the server must still refuse. | G57: Done | H57: Same server-side RBAC as A5/A6 — every endpoint re-checks role, permission and ownership regardless of client; tests/security-adversarial.test.js "privilege escalation", "a self-declared role in the signup body does not grant it" | I57: 2026-09-25
A58: G7 | B58: G · Mobile app security | C58: No payment release capability exists in the app; approval is a web-only function under the Client's control | D58: App quotation, p6 | E58: No release or approval endpoint is reachable with a mobile client token. Enforce server-side by client type, not by hiding the screen. | F58: Call the release endpoint with a mobile token — must be refused. | G58: N/A | H58: — | I58: 2026-09-25 | J58: No release/approval endpoint exists at all in Phase 1 (escrow is Phase 2). The rule is recorded in CLAUDE.md rule 6 for Phase 2.
A59: G8 | B59: G · Mobile app security | C59: Payout account changes made from the app follow the same verification, cooling-off and alerting rules as the web platform | D59: App quotation, p6 | E59: The same server-side rules apply regardless of the client. There is no mobile-specific shortcut. | F59: Change a payout account from the app and confirm cooling-off and the out-of-band alert both fire. | G59: N/A | H59: — | I59: 2026-09-25 | J59: Payout accounts are Phase 2.

Sheet Summary
A1: Security control coverage
A2: Counts update automatically from the Controls sheet.
A4: Category | B4: Total | C4: Done | D4: In progress | E4: Not started | F4: N/A | G4: % complete
A5: A · Authentication & access | B5: =COUNTIF(Controls!$B$2:$B$59,$A5) | C5: =COUNTIFS(Controls!$B$2:$B$59,$A5,Controls!$G$2:$G$59,"Done") | D5: =COUNTIFS(Controls!$B$2:$B$59,$A5,Controls!$G$2:$G$59,"In progress") | E5: =COUNTIFS(Controls!$B$2:$B$59,$A5,Controls!$G$2:$G$59,"Not started") | F5: =COUNTIFS(Controls!$B$2:$B$59,$A5,Controls!$G$2:$G$59,"N/A") | G5: =IFERROR((C5+F5)/B5,0)
A6: B · Application security | B6: =COUNTIF(Controls!$B$2:$B$59,$A6) | C6: =COUNTIFS(Controls!$B$2:$B$59,$A6,Controls!$G$2:$G$59,"Done") | D6: =COUNTIFS(Controls!$B$2:$B$59,$A6,Controls!$G$2:$G$59,"In progress") | E6: =COUNTIFS(Controls!$B$2:$B$59,$A6,Controls!$G$2:$G$59,"Not started") | F6: =COUNTIFS(Controls!$B$2:$B$59,$A6,Controls!$G$2:$G$59,"N/A") | G6: =IFERROR((C6+F6)/B6,0)
A7: C · Payment & escrow | B7: =COUNTIF(Controls!$B$2:$B$59,$A7) | C7: =COUNTIFS(Controls!$B$2:$B$59,$A7,Controls!$G$2:$G$59,"Done") | D7: =COUNTIFS(Controls!$B$2:$B$59,$A7,Controls!$G$2:$G$59,"In progress") | E7: =COUNTIFS(Controls!$B$2:$B$59,$A7,Controls!$G$2:$G$59,"Not started") | F7: =COUNTIFS(Controls!$B$2:$B$59,$A7,Controls!$G$2:$G$59,"N/A") | G7: =IFERROR((C7+F7)/B7,0)
A8: D · Contract & eSign integrity | B8: =COUNTIF(Controls!$B$2:$B$59,$A8) | C8: =COUNTIFS(Controls!$B$2:$B$59,$A8,Controls!$G$2:$G$59,"Done") | D8: =COUNTIFS(Controls!$B$2:$B$59,$A8,Controls!$G$2:$G$59,"In progress") | E8: =COUNTIFS(Controls!$B$2:$B$59,$A8,Controls!$G$2:$G$59,"Not started") | F8: =COUNTIFS(Controls!$B$2:$B$59,$A8,Controls!$G$2:$G$59,"N/A") | G8: =IFERROR((C8+F8)/B8,0)
A9: E · Data protection | B9: =COUNTIF(Controls!$B$2:$B$59,$A9) | C9: =COUNTIFS(Controls!$B$2:$B$59,$A9,Controls!$G$2:$G$59,"Done") | D9: =COUNTIFS(Controls!$B$2:$B$59,$A9,Controls!$G$2:$G$59,"In progress") | E9: =COUNTIFS(Controls!$B$2:$B$59,$A9,Controls!$G$2:$G$59,"Not started") | F9: =COUNTIFS(Controls!$B$2:$B$59,$A9,Controls!$G$2:$G$59,"N/A") | G9: =IFERROR((C9+F9)/B9,0)
A10: F · Infrastructure & operations | B10: =COUNTIF(Controls!$B$2:$B$59,$A10) | C10: =COUNTIFS(Controls!$B$2:$B$59,$A10,Controls!$G$2:$G$59,"Done") | D10: =COUNTIFS(Controls!$B$2:$B$59,$A10,Controls!$G$2:$G$59,"In progress") | E10: =COUNTIFS(Controls!$B$2:$B$59,$A10,Controls!$G$2:$G$59,"Not started") | F10: =COUNTIFS(Controls!$B$2:$B$59,$A10,Controls!$G$2:$G$59,"N/A") | G10: =IFERROR((C10+F10)/B10,0)
A11: G · Mobile app security | B11: =COUNTIF(Controls!$B$2:$B$59,$A11) | C11: =COUNTIFS(Controls!$B$2:$B$59,$A11,Controls!$G$2:$G$59,"Done") | D11: =COUNTIFS(Controls!$B$2:$B$59,$A11,Controls!$G$2:$G$59,"In progress") | E11: =COUNTIFS(Controls!$B$2:$B$59,$A11,Controls!$G$2:$G$59,"Not started") | F11: =COUNTIFS(Controls!$B$2:$B$59,$A11,Controls!$G$2:$G$59,"N/A") | G11: =IFERROR((C11+F11)/B11,0)
A12: TOTAL | B12: =SUM(B5:B11) | C12: =SUM(C5:C11) | D12: =SUM(D5:D11) | E12: =SUM(E5:E11) | F12: =SUM(F5:F11) | G12: =IFERROR((C12+F12)/B12,0)
A14: Every control listed is committed to in the Rev 02 quotations (web pages 10–11 and 7–8, app page 6). Nothing here is optional scope.
